chatgpt_cli/__init__.py
chatgpt_cli/arguement_validator.py
chatgpt_cli/code_parser.py
chatgpt_cli/gpt_request.py
chatgpt_cli/main.py
chatgpt_cli/commands/__init__.py
chatgpt_cli/commands/code_edit.py
chatgpt_cli/commands/review_to_file.py
chatgpt_cli/commands/set_api_key.py
gpt_code_edit-1.0.6.dist-info/METADATA
gpt_code_edit-1.0.6.dist-info/WHEEL
gpt_code_edit-1.0.6.dist-info/entry_points.txt
gpt_code_edit-1.0.6.dist-info/top_level.txt
gpt_code_edit-1.0.6.dist-info/RECORD
