Metadata-Version: 2.1
Name: gpt-code-edit
Version: 1.0.6
Summary: A command line interface that allows you to target specific functions, classes, or methods in a file and use chatgpt to perform several edits including refactoring, adding comments, adding docstrings, or adding error handling.
Home-page: https://github.com/ben-23-96/chatgpt_code_improve_cli
Author: Ben Speakman
Author-email: benspeakman23@yahoo.com
License: UNKNOWN
Platform: UNKNOWN
Classifier: License :: OSI Approved :: MIT License
Classifier: Programming Language :: Python
Classifier: Programming Language :: Python :: 3
Classifier: Programming Language :: Python :: 3.6
Classifier: Programming Language :: Python :: 3.7
Classifier: Programming Language :: Python :: 3.8
Classifier: Programming Language :: Python :: 3.9
Requires-Dist: aiohttp (==3.8.4)
Requires-Dist: markdown-it-py (==3.0.0)
Requires-Dist: redbaron (==0.9.2)
Requires-Dist: tqdm (==4.65.0)
